spotpl/__init__.py
spotpl/spotpl.py
spotpl-1.1.0.dist-info/LICENSE
spotpl-1.1.0.dist-info/METADATA
spotpl-1.1.0.dist-info/WHEEL
spotpl-1.1.0.dist-info/entry_points.txt
spotpl-1.1.0.dist-info/top_level.txt
spotpl-1.1.0.dist-info/RECORD
