Metadata-Version: 2.1
Name: spotpl
Version: 1.1.0
Summary: Download youtube songs in mp3 format and plays them
Home-page: https://github.com/rpotter12/spotify-downloader-music-player
Author: Rohit Potter
Author-email: rohitpotter12@gmail.com
License: MIT
Download-URL: https://pypi.org/project/spotpl/
Keywords: spotify,downloader,download,music,youtube,mp3,album,metadata
Platform: UNKNOWN
Classifier: Programming Language :: Python
Classifier: Programming Language :: Python :: 3
Classifier: Programming Language :: Python :: 3.4
Classifier: Programming Language :: Python :: 3.5
Classifier: Programming Language :: Python :: 3.6
Classifier: Programming Language :: Python :: 3.7
Classifier: Programming Language :: Python :: 3 :: Only
Classifier: License :: OSI Approved :: MIT License
Classifier: Operating System :: OS Independent
Requires-Python: >=3.4
Requires-Dist: spotdl (>=1.2.0)
